{
    "ramp": "increases available mana",
    "mana_fixing": "helps produce correct colors",
    "mana_dork": "creature that taps for mana",
    "rock": "artifact that produces mana",
    "mana_sink": "uses excess mana repeatedly",
    "card_draw": "draws one or more cards",
    "card_selection": "filters or manipulates draws",
    "cantrip": "draws a card with minimal cost",
    "tutor": "searches library for specific card",
    "removal": "eliminates opposing permanents",
    "spot_removal": "removes a single target",
    "board_wipe": "clears multiple permanents",
    "counterspell": "counters spells on the stack",
    "protection": "prevents damage or targeting",
    "graveyard_hate": "disrupts graveyards",
    "recursion": "returns cards from graveyard",
    "reanimator": "puts creatures from graveyard to battlefield",
    "self_mill": "puts own cards into graveyard",
    "mill": "puts opponent cards into graveyard",
    "discard": "forces players to discard cards",
    "discard_matters": "benefits from discarding",
    "token_maker": "creates creature or artifact tokens",
    "token_payoff": "benefits from having tokens",
    "go_wide": "rewards many small creatures",
    "go_tall": "rewards one large creature",
    "sacrifice_outlet": "allows sacrificing permanents",
    "sac_fodder": "cheap expendable permanent",
    "death_payoff": "benefits when creatures die",
    "lifegain_enabler": "causes life gain",
    "lifegain_payoff": "benefits from life gain",
    "etb": "triggers on entering battlefield",
    "ltb": "triggers on leaving battlefield",
    "blink": "exiles and returns permanents",
    "spellslinger": "rewards casting spells",
    "storm": "benefits from multiple spells cast",
    "prowess": "gains stats from noncreature spells",
    "artifacts_matter": "benefits from artifacts",
    "enchantments_matter": "benefits from enchantments",
    "lands_matter": "benefits from lands",
    "counters": "places counters on permanents",
    "counters_payoff": "benefits from counters",
    "proliferate": "increases existing counters",
    "treasure": "creates or uses treasure tokens",
    "burn": "deals direct damage to players or creatures",
    "equipment": "interacts with equipment",
    "aura": "interacts with auras",
    "tribal": "benefits from creature types",
    "value_engine": "generates repeated advantage",
    "card_advantage": "produces more cards than opponent",
    "tempo": "gains advantage through efficiency",
    "threat": "applies pressure to win game",
    "evasive_threat": "hard to block effectively",
    "sticky_threat": "hard to remove or replace",
    "finisher": "wins the game if unanswered",
    "build_around": "rewards synergy-focused decks",
    "synergy_piece": "supports a specific strategy",
    "combo_piece": "part of a game-winning combo",
    "early_play": "useful in early turns",
    "midgame_play": "strong in midgame",
    "top_end": "high-cost late game card",
    "cheap_interaction": "low-cost disruption",
    "combat_trick": "affects combat temporarily",
    "stax": "limits opponent resources or actions",
    "tax": "increases costs for opponents",
    "lock_piece": "restricts opponent options heavily",
    "graveyard_value": "gains value from graveyard use",
    "land_ramp": "puts lands into play",
    "landfall": "triggers when lands enter",
    "draw_engine": "repeatable card draw source",
    "life_drain": "causes life loss and gain",
    "aristocrats": "sacrifice and death synergy",
    "copy": "copies spells or permanents",
    "clone": "copies creatures",
    "untap": "untaps permanents for reuse",
    "haste_enabler": "grants haste to creatures",
    "evasion_enabler": "grants unblockable or evasion",
    "protection_enabler": "grants hexproof or protection",
    "color_intensive": "requires heavy color commitment",
    "synergy_dependent": "weak without synergy",
    "standalone_good": "strong without synergy",
    "utility_land": "land with additional effect"
}